nil_lib/__init__.py
nil_lib-2.1.1.dist-info/LICENCE.md
nil_lib-2.1.1.dist-info/METADATA
nil_lib-2.1.1.dist-info/WHEEL
nil_lib-2.1.1.dist-info/entry_points.txt
nil_lib-2.1.1.dist-info/top_level.txt
nil_lib-2.1.1.dist-info/RECORD
