Metadata-Version: 2.1
Name: nil-lib
Version: 2.1.1
Summary: Python libary of switch and various commands
Author-email: Katlin Sampson <katlinvsampson@gmail.com>
Project-URL: Homepage, https://github.com/Niltak/nil_lib
Project-URL: Bug Tracker, https://github.com/Niltak/nil_lib/issues
Keywords: netmiko,network,DevNet,NetOps
Classifier: Programming Language :: Python
Classifier: Programming Language :: Python :: 3
Requires-Python: >=3.9
License-File: LICENCE.md
Requires-Dist: netmiko >=3.4.0
Requires-Dist: pyyaml
Requires-Dist: textfsm
